{"nodes": [{"id": "d_coders_eduvers_backend_src_users_users_service_ts", "label": "users.service.ts", "file_type": "code", "source_file": "D:\\coders\\eduvers\\backend\\src\\users\\users.service.ts", "source_location": "L1"}, {"id": "users_service_usersservice", "label": "UsersService", "file_type": "code", "source_file": "D:\\coders\\eduvers\\backend\\src\\users\\users.service.ts", "source_location": "L7"}, {"id": "users_service_usersservice_constructor", "label": ".constructor()", "file_type": "code", "source_file": "D:\\coders\\eduvers\\backend\\src\\users\\users.service.ts", "source_location": "L8"}, {"id": "users_service_usersservice_createuser", "label": ".createUser()", "file_type": "code", "source_file": "D:\\coders\\eduvers\\backend\\src\\users\\users.service.ts", "source_location": "L13"}, {"id": "users_service_usersservice_getuser", "label": ".getUser()", "file_type": "code", "source_file": "D:\\coders\\eduvers\\backend\\src\\users\\users.service.ts", "source_location": "L58"}, {"id": "users_service_usersservice_listusers", "label": ".listUsers()", "file_type": "code", "source_file": "D:\\coders\\eduvers\\backend\\src\\users\\users.service.ts", "source_location": "L75"}, {"id": "users_service_usersservice_updateuser", "label": ".updateUser()", "file_type": "code", "source_file": "D:\\coders\\eduvers\\backend\\src\\users\\users.service.ts", "source_location": "L117"}, {"id": "users_service_usersservice_changepassword", "label": ".changePassword()", "file_type": "code", "source_file": "D:\\coders\\eduvers\\backend\\src\\users\\users.service.ts", "source_location": "L150"}, {"id": "users_service_usersservice_deactivateuser", "label": ".deactivateUser()", "file_type": "code", "source_file": "D:\\coders\\eduvers\\backend\\src\\users\\users.service.ts", "source_location": "L186"}, {"id": "users_service_usersservice_reactivateuser", "label": ".reactivateUser()", "file_type": "code", "source_file": "D:\\coders\\eduvers\\backend\\src\\users\\users.service.ts", "source_location": "L208"}, {"id": "users_service_usersservice_listroles", "label": ".listRoles()", "file_type": "code", "source_file": "D:\\coders\\eduvers\\backend\\src\\users\\users.service.ts", "source_location": "L230"}, {"id": "users_service_usersservice_formatuserresponse", "label": ".formatUserResponse()", "file_type": "code", "source_file": "D:\\coders\\eduvers\\backend\\src\\users\\users.service.ts", "source_location": "L237"}], "edges": [{"source": "d_coders_eduvers_backend_src_users_users_service_ts", "target": "common", "relation": "imports_from", "confidence": "EXTRACTED", "source_file": "D:\\coders\\eduvers\\backend\\src\\users\\users.service.ts", "source_location": "L1", "weight": 1.0}, {"source": "d_coders_eduvers_backend_src_users_users_service_ts", "target": "d_coders_eduvers_backend_src_common_prisma_prisma_service", "relation": "imports_from", "confidence": "EXTRACTED", "source_file": "D:\\coders\\eduvers\\backend\\src\\users\\users.service.ts", "source_location": "L2", "weight": 1.0}, {"source": "d_coders_eduvers_backend_src_users_users_service_ts", "target": "d_coders_eduvers_backend_src_auth_auth_service", "relation": "imports_from", "confidence": "EXTRACTED", "source_file": "D:\\coders\\eduvers\\backend\\src\\users\\users.service.ts", "source_location": "L3", "weight": 1.0}, {"source": "d_coders_eduvers_backend_src_users_users_service_ts", "target": "d_coders_eduvers_backend_src_users_dto_user_dto", "relation": "imports_from", "confidence": "EXTRACTED", "source_file": "D:\\coders\\eduvers\\backend\\src\\users\\users.service.ts", "source_location": "L4", "weight": 1.0}, {"source": "d_coders_eduvers_backend_src_users_users_service_ts", "target": "users_service_usersservice", "relation": "contains", "confidence": "EXTRACTED", "source_file": "D:\\coders\\eduvers\\backend\\src\\users\\users.service.ts", "source_location": "L7", "weight": 1.0}, {"source": "users_service_usersservice", "target": "users_service_usersservice_constructor", "relation": "method", "confidence": "EXTRACTED", "source_file": "D:\\coders\\eduvers\\backend\\src\\users\\users.service.ts", "source_location": "L8", "weight": 1.0}, {"source": "users_service_usersservice", "target": "users_service_usersservice_createuser", "relation": "method", "confidence": "EXTRACTED", "source_file": "D:\\coders\\eduvers\\backend\\src\\users\\users.service.ts", "source_location": "L13", "weight": 1.0}, {"source": "users_service_usersservice", "target": "users_service_usersservice_getuser", "relation": "method", "confidence": "EXTRACTED", "source_file": "D:\\coders\\eduvers\\backend\\src\\users\\users.service.ts", "source_location": "L58", "weight": 1.0}, {"source": "users_service_usersservice", "target": "users_service_usersservice_listusers", "relation": "method", "confidence": "EXTRACTED", "source_file": "D:\\coders\\eduvers\\backend\\src\\users\\users.service.ts", "source_location": "L75", "weight": 1.0}, {"source": "users_service_usersservice", "target": "users_service_usersservice_updateuser", "relation": "method", "confidence": "EXTRACTED", "source_file": "D:\\coders\\eduvers\\backend\\src\\users\\users.service.ts", "source_location": "L117", "weight": 1.0}, {"source": "users_service_usersservice", "target": "users_service_usersservice_changepassword", "relation": "method", "confidence": "EXTRACTED", "source_file": "D:\\coders\\eduvers\\backend\\src\\users\\users.service.ts", "source_location": "L150", "weight": 1.0}, {"source": "users_service_usersservice", "target": "users_service_usersservice_deactivateuser", "relation": "method", "confidence": "EXTRACTED", "source_file": "D:\\coders\\eduvers\\backend\\src\\users\\users.service.ts", "source_location": "L186", "weight": 1.0}, {"source": "users_service_usersservice", "target": "users_service_usersservice_reactivateuser", "relation": "method", "confidence": "EXTRACTED", "source_file": "D:\\coders\\eduvers\\backend\\src\\users\\users.service.ts", "source_location": "L208", "weight": 1.0}, {"source": "users_service_usersservice", "target": "users_service_usersservice_listroles", "relation": "method", "confidence": "EXTRACTED", "source_file": "D:\\coders\\eduvers\\backend\\src\\users\\users.service.ts", "source_location": "L230", "weight": 1.0}, {"source": "users_service_usersservice", "target": "users_service_usersservice_formatuserresponse", "relation": "method", "confidence": "EXTRACTED", "source_file": "D:\\coders\\eduvers\\backend\\src\\users\\users.service.ts", "source_location": "L237", "weight": 1.0}, {"source": "users_service_usersservice_createuser", "target": "users_service_usersservice_formatuserresponse", "relation": "calls", "confidence": "EXTRACTED", "source_file": "D:\\coders\\eduvers\\backend\\src\\users\\users.service.ts", "source_location": "L55", "weight": 1.0}, {"source": "users_service_usersservice_getuser", "target": "users_service_usersservice_formatuserresponse", "relation": "calls", "confidence": "EXTRACTED", "source_file": "D:\\coders\\eduvers\\backend\\src\\users\\users.service.ts", "source_location": "L72", "weight": 1.0}, {"source": "users_service_usersservice_updateuser", "target": "users_service_usersservice_formatuserresponse", "relation": "calls", "confidence": "EXTRACTED", "source_file": "D:\\coders\\eduvers\\backend\\src\\users\\users.service.ts", "source_location": "L147", "weight": 1.0}, {"source": "users_service_usersservice_deactivateuser", "target": "users_service_usersservice_formatuserresponse", "relation": "calls", "confidence": "EXTRACTED", "source_file": "D:\\coders\\eduvers\\backend\\src\\users\\users.service.ts", "source_location": "L205", "weight": 1.0}, {"source": "users_service_usersservice_reactivateuser", "target": "users_service_usersservice_formatuserresponse", "relation": "calls", "confidence": "EXTRACTED", "source_file": "D:\\coders\\eduvers\\backend\\src\\users\\users.service.ts", "source_location": "L227", "weight": 1.0}], "raw_calls": [{"caller_nid": "users_service_usersservice_createuser", "callee": "findUnique", "source_file": "D:\\coders\\eduvers\\backend\\src\\users\\users.service.ts", "source_location": "L15"}, {"caller_nid": "users_service_usersservice_createuser", "callee": "findUnique", "source_file": "D:\\coders\\eduvers\\backend\\src\\users\\users.service.ts", "source_location": "L24"}, {"caller_nid": "users_service_usersservice_createuser", "callee": "hashPassword", "source_file": "D:\\coders\\eduvers\\backend\\src\\users\\users.service.ts", "source_location": "L33"}, {"caller_nid": "users_service_usersservice_createuser", "callee": "create", "source_file": "D:\\coders\\eduvers\\backend\\src\\users\\users.service.ts", "source_location": "L38"}, {"caller_nid": "users_service_usersservice_getuser", "callee": "findUnique", "source_file": "D:\\coders\\eduvers\\backend\\src\\users\\users.service.ts", "source_location": "L59"}, {"caller_nid": "users_service_usersservice_listusers", "callee": "max", "source_file": "D:\\coders\\eduvers\\backend\\src\\users\\users.service.ts", "source_location": "L76"}, {"caller_nid": "users_service_usersservice_listusers", "callee": "parseInt", "source_file": "D:\\coders\\eduvers\\backend\\src\\users\\users.service.ts", "source_location": "L76"}, {"caller_nid": "users_service_usersservice_listusers", "callee": "String", "source_file": "D:\\coders\\eduvers\\backend\\src\\users\\users.service.ts", "source_location": "L76"}, {"caller_nid": "users_service_usersservice_listusers", "callee": "max", "source_file": "D:\\coders\\eduvers\\backend\\src\\users\\users.service.ts", "source_location": "L77"}, {"caller_nid": "users_service_usersservice_listusers", "callee": "parseInt", "source_file": "D:\\coders\\eduvers\\backend\\src\\users\\users.service.ts", "source_location": "L77"}, {"caller_nid": "users_service_usersservice_listusers", "callee": "String", "source_file": "D:\\coders\\eduvers\\backend\\src\\users\\users.service.ts", "source_location": "L77"}, {"caller_nid": "users_service_usersservice_listusers", "callee": "all", "source_file": "D:\\coders\\eduvers\\backend\\src\\users\\users.service.ts", "source_location": "L91"}, {"caller_nid": "users_service_usersservice_listusers", "callee": "findMany", "source_file": "D:\\coders\\eduvers\\backend\\src\\users\\users.service.ts", "source_location": "L92"}, {"caller_nid": "users_service_usersservice_listusers", "callee": "count", "source_file": "D:\\coders\\eduvers\\backend\\src\\users\\users.service.ts", "source_location": "L103"}, {"caller_nid": "users_service_usersservice_listusers", "callee": "map", "source_file": "D:\\coders\\eduvers\\backend\\src\\users\\users.service.ts", "source_location": "L109"}, {"caller_nid": "users_service_usersservice_updateuser", "callee": "findUnique", "source_file": "D:\\coders\\eduvers\\backend\\src\\users\\users.service.ts", "source_location": "L118"}, {"caller_nid": "users_service_usersservice_updateuser", "callee": "findUnique", "source_file": "D:\\coders\\eduvers\\backend\\src\\users\\users.service.ts", "source_location": "L128"}, {"caller_nid": "users_service_usersservice_updateuser", "callee": "update", "source_file": "D:\\coders\\eduvers\\backend\\src\\users\\users.service.ts", "source_location": "L137"}, {"caller_nid": "users_service_usersservice_changepassword", "callee": "findUnique", "source_file": "D:\\coders\\eduvers\\backend\\src\\users\\users.service.ts", "source_location": "L154"}, {"caller_nid": "users_service_usersservice_changepassword", "callee": "validatePassword", "source_file": "D:\\coders\\eduvers\\backend\\src\\users\\users.service.ts", "source_location": "L163"}, {"caller_nid": "users_service_usersservice_changepassword", "callee": "hashPassword", "source_file": "D:\\coders\\eduvers\\backend\\src\\users\\users.service.ts", "source_location": "L173"}, {"caller_nid": "users_service_usersservice_changepassword", "callee": "update", "source_file": "D:\\coders\\eduvers\\backend\\src\\users\\users.service.ts", "source_location": "L178"}, {"caller_nid": "users_service_usersservice_deactivateuser", "callee": "findUnique", "source_file": "D:\\coders\\eduvers\\backend\\src\\users\\users.service.ts", "source_location": "L187"}, {"caller_nid": "users_service_usersservice_deactivateuser", "callee": "update", "source_file": "D:\\coders\\eduvers\\backend\\src\\users\\users.service.ts", "source_location": "L195"}, {"caller_nid": "users_service_usersservice_reactivateuser", "callee": "findUnique", "source_file": "D:\\coders\\eduvers\\backend\\src\\users\\users.service.ts", "source_location": "L209"}, {"caller_nid": "users_service_usersservice_reactivateuser", "callee": "update", "source_file": "D:\\coders\\eduvers\\backend\\src\\users\\users.service.ts", "source_location": "L217"}, {"caller_nid": "users_service_usersservice_listroles", "callee": "findMany", "source_file": "D:\\coders\\eduvers\\backend\\src\\users\\users.service.ts", "source_location": "L231"}]}