{"nodes": [{"id": "d_coders_eduvers_backend_src_users_dto_user_dto_ts", "label": "user.dto.ts", "file_type": "code", "source_file": "D:\\coders\\eduvers\\backend\\src\\users\\dto\\user.dto.ts", "source_location": "L1"}, {"id": "user_dto_createuserdto", "label": "CreateUserDto", "file_type": "code", "source_file": "D:\\coders\\eduvers\\backend\\src\\users\\dto\\user.dto.ts", "source_location": "L3"}, {"id": "user_dto_updateuserdto", "label": "UpdateUserDto", "file_type": "code", "source_file": "D:\\coders\\eduvers\\backend\\src\\users\\dto\\user.dto.ts", "source_location": "L24"}, {"id": "user_dto_changepassworddto", "label": "ChangePasswordDto", "file_type": "code", "source_file": "D:\\coders\\eduvers\\backend\\src\\users\\dto\\user.dto.ts", "source_location": "L44"}, {"id": "user_dto_userresponsedto", "label": "UserResponseDto", "file_type": "code", "source_file": "D:\\coders\\eduvers\\backend\\src\\users\\dto\\user.dto.ts", "source_location": "L54"}, {"id": "user_dto_userslistresponsedto", "label": "UsersListResponseDto", "file_type": "code", "source_file": "D:\\coders\\eduvers\\backend\\src\\users\\dto\\user.dto.ts", "source_location": "L68"}], "edges": [{"source": "d_coders_eduvers_backend_src_users_dto_user_dto_ts", "target": "class_validator", "relation": "imports_from", "confidence": "EXTRACTED", "source_file": "D:\\coders\\eduvers\\backend\\src\\users\\dto\\user.dto.ts", "source_location": "L1", "weight": 1.0}, {"source": "d_coders_eduvers_backend_src_users_dto_user_dto_ts", "target": "user_dto_createuserdto", "relation": "contains", "confidence": "EXTRACTED", "source_file": "D:\\coders\\eduvers\\backend\\src\\users\\dto\\user.dto.ts", "source_location": "L3", "weight": 1.0}, {"source": "d_coders_eduvers_backend_src_users_dto_user_dto_ts", "target": "user_dto_updateuserdto", "relation": "contains", "confidence": "EXTRACTED", "source_file": "D:\\coders\\eduvers\\backend\\src\\users\\dto\\user.dto.ts", "source_location": "L24", "weight": 1.0}, {"source": "d_coders_eduvers_backend_src_users_dto_user_dto_ts", "target": "user_dto_changepassworddto", "relation": "contains", "confidence": "EXTRACTED", "source_file": "D:\\coders\\eduvers\\backend\\src\\users\\dto\\user.dto.ts", "source_location": "L44", "weight": 1.0}, {"source": "d_coders_eduvers_backend_src_users_dto_user_dto_ts", "target": "user_dto_userresponsedto", "relation": "contains", "confidence": "EXTRACTED", "source_file": "D:\\coders\\eduvers\\backend\\src\\users\\dto\\user.dto.ts", "source_location": "L54", "weight": 1.0}, {"source": "d_coders_eduvers_backend_src_users_dto_user_dto_ts", "target": "user_dto_userslistresponsedto", "relation": "contains", "confidence": "EXTRACTED", "source_file": "D:\\coders\\eduvers\\backend\\src\\users\\dto\\user.dto.ts", "source_location": "L68", "weight": 1.0}], "raw_calls": []}