{"nodes": [{"id": "d_coders_eduvers_backend_src_audit_logs_audit_logs_service_ts", "label": "audit-logs.service.ts", "file_type": "code", "source_file": "D:\\coders\\eduvers\\backend\\src\\audit-logs\\audit-logs.service.ts", "source_location": "L1"}, {"id": "audit_logs_service_auditlogsservice", "label": "AuditLogsService", "file_type": "code", "source_file": "D:\\coders\\eduvers\\backend\\src\\audit-logs\\audit-logs.service.ts", "source_location": "L5"}, {"id": "audit_logs_service_auditlogsservice_constructor", "label": ".constructor()", "file_type": "code", "source_file": "D:\\coders\\eduvers\\backend\\src\\audit-logs\\audit-logs.service.ts", "source_location": "L6"}, {"id": "audit_logs_service_auditlogsservice_createauditlog", "label": ".createAuditLog()", "file_type": "code", "source_file": "D:\\coders\\eduvers\\backend\\src\\audit-logs\\audit-logs.service.ts", "source_location": "L8"}, {"id": "audit_logs_service_auditlogsservice_listauditlogs", "label": ".listAuditLogs()", "file_type": "code", "source_file": "D:\\coders\\eduvers\\backend\\src\\audit-logs\\audit-logs.service.ts", "source_location": "L32"}, {"id": "audit_logs_service_auditlogsservice_getauditlog", "label": ".getAuditLog()", "file_type": "code", "source_file": "D:\\coders\\eduvers\\backend\\src\\audit-logs\\audit-logs.service.ts", "source_location": "L100"}], "edges": [{"source": "d_coders_eduvers_backend_src_audit_logs_audit_logs_service_ts", "target": "common", "relation": "imports_from", "confidence": "EXTRACTED", "source_file": "D:\\coders\\eduvers\\backend\\src\\audit-logs\\audit-logs.service.ts", "source_location": "L1", "weight": 1.0}, {"source": "d_coders_eduvers_backend_src_audit_logs_audit_logs_service_ts", "target": "d_coders_eduvers_backend_src_common_prisma_prisma_service", "relation": "imports_from", "confidence": "EXTRACTED", "source_file": "D:\\coders\\eduvers\\backend\\src\\audit-logs\\audit-logs.service.ts", "source_location": "L2", "weight": 1.0}, {"source": "d_coders_eduvers_backend_src_audit_logs_audit_logs_service_ts", "target": "audit_logs_service_auditlogsservice", "relation": "contains", "confidence": "EXTRACTED", "source_file": "D:\\coders\\eduvers\\backend\\src\\audit-logs\\audit-logs.service.ts", "source_location": "L5", "weight": 1.0}, {"source": "audit_logs_service_auditlogsservice", "target": "audit_logs_service_auditlogsservice_constructor", "relation": "method", "confidence": "EXTRACTED", "source_file": "D:\\coders\\eduvers\\backend\\src\\audit-logs\\audit-logs.service.ts", "source_location": "L6", "weight": 1.0}, {"source": "audit_logs_service_auditlogsservice", "target": "audit_logs_service_auditlogsservice_createauditlog", "relation": "method", "confidence": "EXTRACTED", "source_file": "D:\\coders\\eduvers\\backend\\src\\audit-logs\\audit-logs.service.ts", "source_location": "L8", "weight": 1.0}, {"source": "audit_logs_service_auditlogsservice", "target": "audit_logs_service_auditlogsservice_listauditlogs", "relation": "method", "confidence": "EXTRACTED", "source_file": "D:\\coders\\eduvers\\backend\\src\\audit-logs\\audit-logs.service.ts", "source_location": "L32", "weight": 1.0}, {"source": "audit_logs_service_auditlogsservice", "target": "audit_logs_service_auditlogsservice_getauditlog", "relation": "method", "confidence": "EXTRACTED", "source_file": "D:\\coders\\eduvers\\backend\\src\\audit-logs\\audit-logs.service.ts", "source_location": "L100", "weight": 1.0}], "raw_calls": [{"caller_nid": "audit_logs_service_auditlogsservice_createauditlog", "callee": "create", "source_file": "D:\\coders\\eduvers\\backend\\src\\audit-logs\\audit-logs.service.ts", "source_location": "L18"}, {"caller_nid": "audit_logs_service_auditlogsservice_listauditlogs", "callee": "min", "source_file": "D:\\coders\\eduvers\\backend\\src\\audit-logs\\audit-logs.service.ts", "source_location": "L44"}, {"caller_nid": "audit_logs_service_auditlogsservice_listauditlogs", "callee": "max", "source_file": "D:\\coders\\eduvers\\backend\\src\\audit-logs\\audit-logs.service.ts", "source_location": "L44"}, {"caller_nid": "audit_logs_service_auditlogsservice_listauditlogs", "callee": "max", "source_file": "D:\\coders\\eduvers\\backend\\src\\audit-logs\\audit-logs.service.ts", "source_location": "L45"}, {"caller_nid": "audit_logs_service_auditlogsservice_listauditlogs", "callee": "all", "source_file": "D:\\coders\\eduvers\\backend\\src\\audit-logs\\audit-logs.service.ts", "source_location": "L71"}, {"caller_nid": "audit_logs_service_auditlogsservice_listauditlogs", "callee": "findMany", "source_file": "D:\\coders\\eduvers\\backend\\src\\audit-logs\\audit-logs.service.ts", "source_location": "L72"}, {"caller_nid": "audit_logs_service_auditlogsservice_listauditlogs", "callee": "count", "source_file": "D:\\coders\\eduvers\\backend\\src\\audit-logs\\audit-logs.service.ts", "source_location": "L88"}, {"caller_nid": "audit_logs_service_auditlogsservice_getauditlog", "callee": "findUnique", "source_file": "D:\\coders\\eduvers\\backend\\src\\audit-logs\\audit-logs.service.ts", "source_location": "L101"}]}